MyCaesarCipher/__init__.py
MyCaesarCipher/main.py
MyCaesarCipher/tests/MyCaesarCipher_Test.py
MyCaesarCipher/tests/__init__.py
MyCaesarCipher-0.4.1.dist-info/LICENSE
MyCaesarCipher-0.4.1.dist-info/METADATA
MyCaesarCipher-0.4.1.dist-info/WHEEL
MyCaesarCipher-0.4.1.dist-info/top_level.txt
MyCaesarCipher-0.4.1.dist-info/RECORD
