Metadata-Version: 2.1
Name: MyCaesarCipher
Version: 0.4.1
Summary: Simple cryptographic substitution-based cipher for encoding plaintext.
Home-page: https://github.com/schlopp96/MyCaesarCipher
Author: schlopp96
Author-email: schloppdaddy@gmail.com
License: UNKNOWN
Keywords: cryptography,Caesar-Cipher,Caesar,Cipher,encryption,decryption,cryptographic,module,script,encrypt,decrypt,python
Platform: UNKNOWN
Classifier: Development Status :: 3 - Alpha
Classifier: Intended Audience :: Developers
Classifier: Intended Audience :: End Users/Desktop
Classifier: License :: OSI Approved :: GNU General Public License v3 (GPLv3)
Classifier: Natural Language :: English
Classifier: Operating System :: Microsoft :: Windows
Classifier: Programming Language :: Python :: 3
Classifier: Programming Language :: Python :: 3.9
Classifier: Programming Language :: Python :: 3.10
Classifier: Programming Language :: Python :: 3.11
Classifier: Topic :: Software Development :: Libraries :: Python Modules
Classifier: Topic :: Security :: Cryptography
Classifier: Topic :: Utilities
License-File: LICENSE
Requires-Dist: setuptools (>=58.1.0)
